yaml_axis_parser/__init__.py
yaml_axis_parser-0.0.1.dist-info/LICENSE
yaml_axis_parser-0.0.1.dist-info/METADATA
yaml_axis_parser-0.0.1.dist-info/WHEEL
yaml_axis_parser-0.0.1.dist-info/entry_points.txt
yaml_axis_parser-0.0.1.dist-info/top_level.txt
yaml_axis_parser-0.0.1.dist-info/RECORD
