Metadata-Version: 2.1
Name: yaml-axis-parser
Version: 0.0.1
Summary: Tool to output yaml axis combinations
Home-page: https://github.com/raydouglass/yaml-axis-parser
Author: Ray Douglass
Author-email: ray@raydouglass.com
License: UNKNOWN
Project-URL: Bug Tracker, https://github.com/raydouglass/yaml-axis-parser/issues
Platform: UNKNOWN
Classifier: Programming Language :: Python :: 3
Classifier: License :: OSI Approved :: MIT License
Classifier: Operating System :: OS Independent
Requires-Python: >=3.6
License-File: LICENSE
Requires-Dist: pyyaml
